nomad_camels_driver_SweepMe_device/SweepMe_device.py
nomad_camels_driver_SweepMe_device/SweepMe_device_ophyd.py
nomad_camels_driver_SweepMe_device/__init__.py
nomad_camels_driver_SweepMe_device-0.2.0.dist-info/LICENSE.txt
nomad_camels_driver_SweepMe_device-0.2.0.dist-info/METADATA
nomad_camels_driver_SweepMe_device-0.2.0.dist-info/WHEEL
nomad_camels_driver_SweepMe_device-0.2.0.dist-info/top_level.txt
nomad_camels_driver_SweepMe_device-0.2.0.dist-info/RECORD
